pyiec/__init__.py
pyiec-0.1.2.dist-info/LICENSE
pyiec-0.1.2.dist-info/METADATA
pyiec-0.1.2.dist-info/WHEEL
pyiec-0.1.2.dist-info/top_level.txt
pyiec-0.1.2.dist-info/RECORD
